pypackage_skeleton/__init__.py
pypackage_skeleton/py.typed
pypackage_skeleton-0.1.11.dist-info/METADATA
pypackage_skeleton-0.1.11.dist-info/WHEEL
pypackage_skeleton-0.1.11.dist-info/licenses/AUTHORS.rst
pypackage_skeleton-0.1.11.dist-info/licenses/LICENSE
pypackage_skeleton-0.1.11.dist-info/RECORD
